DESCRIPTION.rst
MANIFEST.in
README.rst
setup.cfg
setup.py
daemons/systemd/marcopolomanager.service
daemons/systemv/marcopolomanagerd
etc/marcopolomanager/__init__.py
etc/marcopolomanager/marcopolomanager.cfg
etc/marcopolomanager/managers/__init__.py
etc/marcopolomanager/managers/managers.py
marcopolo_manager.egg-info/PKG-INFO
marcopolo_manager.egg-info/SOURCES.txt
marcopolo_manager.egg-info/dependency_links.txt
marcopolo_manager.egg-info/entry_points.txt
marcopolo_manager.egg-info/not-zip-safe
marcopolo_manager.egg-info/requires.txt
marcopolo_manager.egg-info/top_level.txt
marcopolomanager/__init__.py
marcopolomanager/conf.py
marcopolomanager/marcomanagerreload.py
marcopolomanager/marcopolomanager.py
marcopolomanager/runner.py