Metadata-Version: 1.1
Name: marcopolo-manager
Version: 0.1.1
Summary: A task scheduler with MarcoPolo integration
Home-page: marcopolo.martinarroyo.net
Author: Diego Martín
Author-email: martinarroyo@usal.es
License: MIT
Keywords: marcopolomanager task scheduler
Platform: UNKNOWN
Classifier: Development Status :: 3 - Alpha
Classifier: Programming Language :: Python :: 2.7
Classifier: Programming Language :: Python :: 3.4
Classifier: Development Status :: 3 - Alpha
Classifier: Intended Audience :: System Administrators
Classifier: Topic :: Software Development :: Build Tools
Classifier: Topic :: System :: Networking
Classifier: License :: OSI Approved :: Mozilla Public License 2.0 (MPL 2.0)
Classifier: Natural Language :: English
Provides: marcopolomanager
